Expression_Database/AE.py
Expression_Database/GEO.py
Expression_Database/__init__.py
Expression_Database/util.py
Expression_Database_NCI-0.0.1.data/data/bin/Rdata_Matrix.R
Expression_Database_NCI-0.0.1.data/data/bin/rma_affy.R
Expression_Database_NCI-0.0.1.data/data/bin/rma_oligo.R
Expression_Database_NCI-0.0.1.dist-info/LICENSE
Expression_Database_NCI-0.0.1.dist-info/METADATA
Expression_Database_NCI-0.0.1.dist-info/WHEEL
Expression_Database_NCI-0.0.1.dist-info/top_level.txt
Expression_Database_NCI-0.0.1.dist-info/RECORD
