Metadata-Version: 2.1
Name: Expression-Database-NCI
Version: 0.0.1
Summary: Toolkits for NCBI GEO and ArrayExpress
Home-page: https://github.com/pypa/Expression_Database
Author: Peng Jiang
Author-email: peng.jiang@nih.gov
License: UNKNOWN
Platform: UNKNOWN
Classifier: Programming Language :: Python :: 3
Classifier: License :: OSI Approved :: MIT License
Classifier: Operating System :: OS Independent
Requires-Python: >=3.6
Requires-Dist: GEOparse
Requires-Dist: Orange3
Requires-Dist: bioservices
